pyrecipepuppy/__init__.py
pyrecipepuppy/recipepuppy.py
pyrecipepuppy-0.0.1.dist-info/LICENSE.txt
pyrecipepuppy-0.0.1.dist-info/METADATA
pyrecipepuppy-0.0.1.dist-info/WHEEL
pyrecipepuppy-0.0.1.dist-info/top_level.txt
pyrecipepuppy-0.0.1.dist-info/RECORD
