Metadata-Version: 2.1
Name: pyrecipepuppy
Version: 0.0.1
Summary: A simple Python wrapper for the Recipe Puppy API
Home-page: https://github.com/crinela/pyrecipepuppy
Author: Crinela Potinteu
Author-email: potinteu.crinela@gmail.com
License: UNKNOWN
Platform: UNKNOWN
Classifier: Programming Language :: Python :: 3
Classifier: License :: OSI Approved :: MIT License
Classifier: Operating System :: OS Independent
Requires-Python: >=3.6
